utify/__init__.py
utify/base.py
utify/cache.py
utify/cli.py
utify/dataframe.py
utify/dataset.py
utify/fastprogress.py
utify/logger.py
utify/plotting.py
utify-0.2.12.dist-info/entry_points.txt
utify-0.2.12.dist-info/WHEEL
utify-0.2.12.dist-info/METADATA
utify-0.2.12.dist-info/RECORD
